github_docs_scraper_capharno/__init__.py
github_docs_scraper_capharno/__main__.py
github_docs_scraper_capharno/cli.py
github_docs_scraper_capharno/core.py
github_docs_scraper_capharno-0.1.5.dist-info/METADATA
github_docs_scraper_capharno-0.1.5.dist-info/WHEEL
github_docs_scraper_capharno-0.1.5.dist-info/entry_points.txt
github_docs_scraper_capharno-0.1.5.dist-info/licenses/LICENSE
github_docs_scraper_capharno-0.1.5.dist-info/RECORD
