Metadata-Version: 2.4
Name: github_docs_scraper_capharno
Version: 0.1.5
Summary: CLI tool to scrape Markdown documentation from GitHub repositories
Project-URL: Homepage, https://github.com/coeur-de-loup/github-docs-scraper
Project-URL: Issues, https://github.com/coeur-de-loup/github-docs-scraper/issues
Author-email: Andy Bourgeois <capharno@gmail.com>
License-File: LICENSE
Keywords: cli,documentation,github,markdown,scraper
Classifier: Development Status :: 3 - Alpha
Classifier: Environment :: Console
Classifier: Intended Audience :: Developers
Classifier: License :: OSI Approved :: MIT License
Classifier: Programming Language :: Python :: 3
Classifier: Programming Language :: Python :: 3.8
Classifier: Programming Language :: Python :: 3.9
Classifier: Programming Language :: Python :: 3.10
Classifier: Programming Language :: Python :: 3.11
Classifier: Programming Language :: Python :: 3.12
Classifier: Topic :: Documentation
Classifier: Topic :: Software Development :: Documentation
Classifier: Topic :: Utilities
Requires-Python: >=3.8
Requires-Dist: click>=8.1.3
Requires-Dist: python-dotenv>=0.21.0
Requires-Dist: requests>=2.28.1
